sitecustomize.py
retracesoftware_autoenable_debug-0.1.3.dist-info/licenses/LICENSE
retracesoftware_autoenable_debug-0.1.3.dist-info/METADATA
retracesoftware_autoenable_debug-0.1.3.dist-info/WHEEL
retracesoftware_autoenable_debug-0.1.3.dist-info/top_level.txt
retracesoftware_autoenable_debug-0.1.3.dist-info/RECORD
