Metadata-Version: 2.4
Name: retracesoftware_autoenable_debug
Version: 0.1.3
Summary: Auto-enable retracesoftware instrumentation
License: Apache-2.0
Requires-Python: >=3.11
License-File: LICENSE
Requires-Dist: retracesoftware_proxy_debug
Dynamic: license-file
